AUTHORS.rst
LICENSE
README.md
setup.py
autocnet/__init__.py
autocnet/config_parser.py
autocnet/sql.py
autocnet.egg-info/PKG-INFO
autocnet.egg-info/SOURCES.txt
autocnet.egg-info/dependency_links.txt
autocnet.egg-info/entry_points.txt
autocnet.egg-info/not-zip-safe
autocnet.egg-info/requires.txt
autocnet.egg-info/top_level.txt
autocnet/camera/__init__.py
autocnet/camera/camera.py
autocnet/camera/utils.py
autocnet/camera/tests/__init__.py
autocnet/camera/tests/test_camera.py
autocnet/camera/tests/test_utils.py
autocnet/cg/__init__.py
autocnet/cg/cg.py
autocnet/cg/change_detection.py
autocnet/cg/tests/__init__.py
autocnet/cg/tests/test_cg.py
autocnet/cg/tests/test_change_detection.py
autocnet/control/__init__.py
autocnet/control/control.py
autocnet/control/tests/__init__.py
autocnet/control/tests/test_control.py
autocnet/examples/__init__.py
autocnet/graph/__init__.py
autocnet/graph/asynchronous_funcs.py
autocnet/graph/cluster_submit.py
autocnet/graph/cluster_submit_single.py
autocnet/graph/edge.py
autocnet/graph/markov_cluster.py
autocnet/graph/network.py
autocnet/graph/node.py
autocnet/graph/tests/__init__.py
autocnet/graph/tests/test_cluster_submit.py
autocnet/graph/tests/test_edge.py
autocnet/graph/tests/test_markov_cluster.py
autocnet/graph/tests/test_network.py
autocnet/graph/tests/test_network_graph.py
autocnet/graph/tests/test_node.py
autocnet/io/__init__.py
autocnet/io/keypoints.py
autocnet/io/network.py
autocnet/io/db/__init__.py
autocnet/io/db/adapters.py
autocnet/io/db/connection.py
autocnet/io/db/controlnetwork.py
autocnet/io/db/model.py
autocnet/io/db/triggers.py
autocnet/io/db/wrappers.py
autocnet/io/db/tests/__init__.py
autocnet/io/db/tests/test_controlnetwork.py
autocnet/io/db/tests/test_model.py
autocnet/io/tests/__init__.py
autocnet/io/tests/test_keypoints.py
autocnet/matcher/__init__.py
autocnet/matcher/cpu_decompose.py
autocnet/matcher/cpu_extractor.py
autocnet/matcher/cpu_matcher.py
autocnet/matcher/cpu_outlier_detector.py
autocnet/matcher/cpu_ring_matcher.py
autocnet/matcher/cross_instrument_matcher.py
autocnet/matcher/cuda_decompose.py
autocnet/matcher/cuda_extractor.py
autocnet/matcher/cuda_matcher.py
autocnet/matcher/cuda_outlier_detector.py
